epyxid/__init__.py
epyxid/__init__.pyi
epyxid/epyxid.cpython-39-aarch64-linux-gnu.so
epyxid/py.typed
epyxid-0.3.5.dist-info/METADATA
epyxid-0.3.5.dist-info/WHEEL
epyxid-0.3.5.dist-info/licenses/LICENSE.txt
epyxid-0.3.5.dist-info/RECORD
