Metadata-Version: 2.4
Name: epyxid
Version: 0.3.5
Classifier: Development Status :: 5 - Production/Stable
Classifier: License :: OSI Approved :: MIT License
Classifier: Programming Language :: Rust
Classifier: Programming Language :: Python
Classifier: Programming Language :: Python :: 3
Classifier: Programming Language :: Python :: 3 :: Only
Classifier: Programming Language :: Python :: 3.8
Classifier: Programming Language :: Python :: 3.9
Classifier: Programming Language :: Python :: 3.10
Classifier: Programming Language :: Python :: 3.11
Classifier: Programming Language :: Python :: 3.12
Classifier: Programming Language :: Python :: 3.13
Classifier: Programming Language :: Python :: 3.14
Classifier: Programming Language :: Python :: Implementation :: CPython
Classifier: Programming Language :: Python :: Implementation :: PyPy
Classifier: Operating System :: POSIX :: Linux
Classifier: Operating System :: Microsoft :: Windows
Classifier: Operating System :: MacOS
Classifier: Typing :: Typed
Classifier: Intended Audience :: Developers
Classifier: Topic :: Software Development :: Libraries :: Python Modules
License-File: LICENSE.txt
Summary: Python wrapper around Rust implementation of XID (Globally Unique ID Generator)
Keywords: rust,xid,pyo3
Home-Page: https://github.com/shpaker/epyxid
Author-email: Aleksandr Shpak <shpaker@gmail.com>
Requires-Python: >=3.8
Project-URL: Homepage, https://github.com/shpaker/epyxid
Project-URL: Repository, https://github.com/shpaker/epyxid
